Metadata-Version: 2.1
Name: django-oscar-promotions
Version: 1.0.0b1
Summary: Promotions for Django Oscar
Home-page: https://github.com/oscaro/django-oscar-promotins
Author: Oscar Team
Author-email: sasha@metaclass.co
License: BSD
Platform: UNKNOWN
Classifier: Development Status :: 4 - Beta
Classifier: Environment :: Web Environment
Classifier: Framework :: Django
Classifier: Framework :: Django :: 2.0
Classifier: Intended Audience :: Developers
Classifier: License :: OSI Approved :: BSD License
Classifier: Operating System :: Unix
Classifier: Programming Language :: Python :: 3
Classifier: Programming Language :: Python :: 3.5
Classifier: Programming Language :: Python :: 3.6
Classifier: Programming Language :: Python :: 3.7
Requires-Dist: django (<2.3,>=1.11)
Requires-Dist: django-oscar (>=2.0)
